{
country: "ca",
frequencyBlocks: [
	{ "start": "0 kHz", "end": "9 kHz" },
	{ "start": "9 kHz", "end": "14 kHz" },
	{ "start": "14 kHz", "end": "19.95 kHz" },
	{ "start": "19.95 kHz", "end": "20.05 kHz" },
	{ "start": "20.05 kHz", "end": "70 kHz" },
	{ "start": "70 kHz", "end": "90 kHz" },
	{ "start": "90 kHz", "end": "110 kHz" },
	{ "start": "110 kHz", "end": "130 kHz" },
	{ "start": "130 kHz", "end": "135.7 kHz" },
	{ "start": "135.7 kHz", "end": "137.8 kHz" },
	{ "start": "137.8 kHz", "end": "160 kHz" },
	{ "start": "160 kHz", "end": "190 kHz" },
	{ "start": "190 kHz", "end": "200 kHz" },
	{ "start": "200 kHz", "end": "285 kHz" },
	{ "start": "285 kHz", "end": "315 kHz" },
	{ "start": "315 kHz", "end": "325 kHz" },
	{ "start": "325 kHz", "end": "335 kHz" },
	{ "start": "335 kHz", "end": "405 kHz" },
	{ "start": "405 kHz", "end": "415 kHz" },
	{ "start": "415 kHz", "end": "495 kHz" },
	{ "start": "495 kHz", "end": "505 kHz" },
	{ "start": "505 kHz", "end": "510 kHz" },
	{ "start": "510 kHz", "end": "525 kHz" },
	{ "start": "525 kHz", "end": "535 kHz" },
	{ "start": "535 kHz", "end": "1605 kHz" },
	{ "start": "1605 kHz", "end": "1705 kHz" },
	{ "start": "1705 kHz", "end": "1800 kHz" },
	{ "start": "1800 kHz", "end": "1850 kHz" },
	{ "start": "1850 kHz", "end": "2000 kHz" },
	{ "start": "2000 kHz", "end": "2065 kHz" },
	{ "start": "2065 kHz", "end": "2107 kHz" },
	{ "start": "2107 kHz", "end": "2170 kHz" },
	{ "start": "2170 kHz", "end": "2173.5 kHz" },
	{ "start": "2173.5 kHz", "end": "2190.5 kHz" },
	{ "start": "2190.5 kHz", "end": "2194 kHz" },
	{ "start": "2194 kHz", "end": "2495 kHz" },
	{ "start": "2495 kHz", "end": "2501 kHz" },
	{ "start": "2501 kHz", "end": "2502 kHz" },
	{ "start": "2502 kHz", "end": "2505 kHz" },
	{ "start": "2505 kHz", "end": "2850 kHz" },
	{ "start": "2850 kHz", "end": "3025 kHz" },
	{ "start": "3025 kHz", "end": "3155 kHz" },
	{ "start": "3155 kHz", "end": "3230 kHz" },
	{ "start": "3230 kHz", "end": "3400 kHz" },
	{ "start": "3400 kHz", "end": "3500 kHz" },
	{ "start": "3500 kHz", "end": "4000 kHz" },
	{ "start": "4000 kHz", "end": "4063 kHz" },
	{ "start": "4063 kHz", "end": "4438 kHz" },
	{ "start": "4438 kHz", "end": "4650 kHz" },
	{ "start": "4650 kHz", "end": "4700 kHz" },
	{ "start": "4700 kHz", "end": "4750 kHz" },
	{ "start": "4750 kHz", "end": "4850 kHz" },
	{ "start": "4850 kHz", "end": "4995 kHz" },
	{ "start": "4995 kHz", "end": "5003 kHz" },
	{ "start": "5003 kHz", "end": "5005 kHz" },
	{ "start": "5005 kHz", "end": "5060 kHz" },
	{ "start": "5060 kHz", "end": "5250 kHz" },
	{ "start": "5250 kHz", "end": "5450 kHz" },
	{ "start": "5450 kHz", "end": "5480 kHz" },
	{ "start": "5480 kHz", "end": "5680 kHz" },
	{ "start": "5680 kHz", "end": "5730 kHz" },
	{ "start": "5730 kHz", "end": "5900 kHz" },
	{ "start": "5900 kHz", "end": "5950 kHz" },
	{ "start": "5950 kHz", "end": "6200 kHz" },
	{ "start": "6200 kHz", "end": "6525 kHz" },
	{ "start": "6525 kHz", "end": "6685 kHz" },
	{ "start": "6685 kHz", "end": "6765 kHz" },
	{ "start": "6765 kHz", "end": "7000 kHz" },
	{ "start": "7000 kHz", "end": "7100 kHz" },
	{ "start": "7100 kHz", "end": "7300 kHz" },
	{ "start": "7300 kHz", "end": "7400 kHz" },
	{ "start": "7400 kHz", "end": "8100 kHz" },
	{ "start": "8100 kHz", "end": "8195 kHz" },
	{ "start": "8195 kHz", "end": "8815 kHz" },
	{ "start": "8815 kHz", "end": "8965 kHz" },
	{ "start": "8965 kHz", "end": "9040 kHz" },
	{ "start": "9040 kHz", "end": "9400 kHz" },
	{ "start": "9400 kHz", "end": "9500 kHz" },
	{ "start": "9500 kHz", "end": "9900 kHz" },
	{ "start": "9900 kHz", "end": "9995 kHz" },
	{ "start": "9995 kHz", "end": "10003 kHz" },
	{ "start": "10003 kHz", "end": "10005 kHz" },
	{ "start": "10005 kHz", "end": "10100 kHz" },
	{ "start": "10100 kHz", "end": "10150 kHz" },
	{ "start": "10150 kHz", "end": "11175 kHz" },
	{ "start": "11175 kHz", "end": "11275 kHz" },
	{ "start": "11275 kHz", "end": "11400 kHz" },
	{ "start": "11400 kHz", "end": "11600 kHz" },
	{ "start": "11600 kHz", "end": "11650 kHz" },
	{ "start": "11650 kHz", "end": "12050 kHz" },
	{ "start": "12050 kHz", "end": "12100 kHz" },
	{ "start": "12100 kHz", "end": "12230 kHz" },
	{ "start": "12230 kHz", "end": "13200 kHz" },
	{ "start": "13200 kHz", "end": "13260 kHz" },
	{ "start": "13260 kHz", "end": "13360 kHz" },
	{ "start": "13360 kHz", "end": "13410 kHz" },
	{ "start": "13410 kHz", "end": "13570 kHz" },
	{ "start": "13570 kHz", "end": "13600 kHz" },
	{ "start": "13600 kHz", "end": "13800 kHz" },
	{ "start": "13800 kHz", "end": "13870 kHz" },
	{ "start": "13870 kHz", "end": "14000 kHz" },
	{ "start": "14000 kHz", "end": "14250 kHz" },
	{ "start": "14250 kHz", "end": "14350 kHz" },
	{ "start": "14350 kHz", "end": "14990 kHz" },
	{ "start": "14990 kHz", "end": "15005 kHz" },
	{ "start": "15005 kHz", "end": "15010 kHz" },
	{ "start": "15010 kHz", "end": "15100 kHz" },
	{ "start": "15100 kHz", "end": "15600 kHz" },
	{ "start": "15600 kHz", "end": "15800 kHz" },
	{ "start": "15800 kHz", "end": "16360 kHz" },
	{ "start": "16360 kHz", "end": "17410 kHz" },
	{ "start": "17410 kHz", "end": "17480 kHz" },
	{ "start": "17480 kHz", "end": "17550 kHz" },
	{ "start": "17550 kHz", "end": "17900 kHz" },
	{ "start": "17900 kHz", "end": "17970 kHz" },
	{ "start": "17970 kHz", "end": "18030 kHz" },
	{ "start": "18030 kHz", "end": "18052 kHz" },
	{ "start": "18052 kHz", "end": "18068 kHz" },
	{ "start": "18068 kHz", "end": "18168 kHz" },
	{ "start": "18168 kHz", "end": "18780 kHz" },
	{ "start": "18780 kHz", "end": "18900 kHz" },
	{ "start": "18900 kHz", "end": "19020 kHz" },
	{ "start": "19020 kHz", "end": "19680 kHz" },
	{ "start": "19680 kHz", "end": "19800 kHz" },
	{ "start": "19800 kHz", "end": "19990 kHz" },
	{ "start": "19990 kHz", "end": "19995 kHz" },
	{ "start": "19995 kHz", "end": "20010 kHz" },
	{ "start": "20010 kHz", "end": "21000 kHz" },
	{ "start": "21000 kHz", "end": "21450 kHz" },
	{ "start": "21450 kHz", "end": "21850 kHz" },
	{ "start": "21850 kHz", "end": "21870 kHz" },
	{ "start": "21870 kHz", "end": "21924 kHz" },
	{ "start": "21924 kHz", "end": "22000 kHz" },
	{ "start": "22000 kHz", "end": "22855 kHz" },
	{ "start": "22855 kHz", "end": "23000 kHz" },
	{ "start": "23000 kHz", "end": "23200 kHz" },
	{ "start": "23200 kHz", "end": "23350 kHz" },
	{ "start": "23350 kHz", "end": "24000 kHz" },
	{ "start": "24000 kHz", "end": "24890 kHz" },
	{ "start": "24.89 MHz", "end": "24.99 MHz" },
	{ "start": "24.99 MHz", "end": "25.005 MHz" },
	{ "start": "25.005 MHz", "end": "25.01 MHz" },
	{ "start": "25.01 MHz", "end": "25.07 MHz" },
	{ "start": "25.07 MHz", "end": "25.21 MHz" },
	{ "start": "25.21 MHz", "end": "25.55 MHz" },
	{ "start": "25.55 MHz", "end": "25.67 MHz" },
	{ "start": "25.67 MHz", "end": "26.1 MHz" },
	{ "start": "26.1 MHz", "end": "26.175 MHz" },
	{ "start": "26.175 MHz", "end": "27.5 MHz" },
	{ "start": "27.5 MHz", "end": "28 MHz" },
	{ "start": "28 MHz", "end": "29.7 MHz" },
	{ "start": "29.7 MHz", "end": "30.005 MHz" },
	{ "start": "30.005 MHz", "end": "30.01 MHz" },
	{ "start": "30.01 MHz", "end": "37.5 MHz" },
	{ "start": "37.5 MHz", "end": "38.25 MHz" },
	{ "start": "38.25 MHz", "end": "39.986 MHz" },
	{ "start": "39.986 MHz", "end": "40.02 MHz" },
	{ "start": "40.02 MHz", "end": "40.98 MHz" },
	{ "start": "40.98 MHz", "end": "41.015 MHz" },
	{ "start": "41.015 MHz", "end": "50 MHz" },
	{ "start": "50 MHz", "end": "54 MHz" },
	{ "start": "54 MHz", "end": "72 MHz" },
	{ "start": "72 MHz", "end": "73 MHz" },
	{ "start": "73 MHz", "end": "74.6 MHz" },
	{ "start": "74.6 MHz", "end": "74.8 MHz" },
	{ "start": "74.8 MHz", "end": "75.2 MHz" },
	{ "start": "75.2 MHz", "end": "76 MHz" },
	{ "start": "76 MHz", "end": "108 MHz" },
	{ "start": "108 MHz", "end": "117.975 MHz" },
	{ "start": "117.975 MHz", "end": "137 MHz" },
	{ "start": "137 MHz", "end": "138 MHz" },
	{ "start": "138 MHz", "end": "144 MHz" },
	{ "start": "144 MHz", "end": "146 MHz" },
	{ "start": "146 MHz", "end": "148 MHz" },
	{ "start": "148 MHz", "end": "149.9 MHz" },
	{ "start": "149.9 MHz", "end": "150.05 MHz" },
	{ "start": "150.05 MHz", "end": "156.4875 MHz" },
	{ "start": "156.4875 MHz", "end": "156.5625 MHz" },
	{ "start": "156.5625 MHz", "end": "156.7625 MHz" },
	{ "start": "156.7625 MHz", "end": "156.8375 MHz" },
	{ "start": "156.8375 MHz", "end": "174 MHz" },
	{ "start": "174 MHz", "end": "216 MHz" },
	{ "start": "216 MHz", "end": "220 MHz" },
	{ "start": "220 MHz", "end": "222 MHz" },
	{ "start": "222 MHz", "end": "225 MHz" },
	{ "start": "225 MHz", "end": "312 MHz" },
	{ "start": "312 MHz", "end": "315 MHz" },
	{ "start": "315 MHz", "end": "328.6 MHz" },
	{ "start": "328.6 MHz", "end": "335.4 MHz" },
	{ "start": "335.4 MHz", "end": "387 MHz" },
	{ "start": "387 MHz", "end": "390 MHz" },
	{ "start": "390 MHz", "end": "399.9 MHz" },
	{ "start": "399.9 MHz", "end": "400.05 MHz" },
	{ "start": "400.05 MHz", "end": "400.15 MHz" },
	{ "start": "400.15 MHz", "end": "401 MHz" },
	{ "start": "401 MHz", "end": "402 MHz" },
	{ "start": "402 MHz", "end": "403 MHz" },
	{ "start": "403 MHz", "end": "406 MHz" },
	{ "start": "406 MHz", "end": "406.1 MHz" },
	{ "start": "406.1 MHz", "end": "410 MHz" },
	{ "start": "410 MHz", "end": "414 MHz" },
	{ "start": "414 MHz", "end": "415 MHz" },
	{ "start": "415 MHz", "end": "419 MHz" },
	{ "start": "419 MHz", "end": "420 MHz" },
	{ "start": "420 MHz", "end": "430 MHz" },
	{ "start": "430 MHz", "end": "432 MHz" },
	{ "start": "432 MHz", "end": "438 MHz" },
	{ "start": "438 MHz", "end": "450 MHz" },
	{ "start": "450 MHz", "end": "455 MHz" },
	{ "start": "455 MHz", "end": "456 MHz" },
	{ "start": "456 MHz", "end": "459 MHz" },
	{ "start": "459 MHz", "end": "460 MHz" },
	{ "start": "460 MHz", "end": "470 MHz" },
	{ "start": "470 MHz", "end": "608 MHz" },
	{ "start": "608 MHz", "end": "614 MHz" },
	{ "start": "614 MHz", "end": "746 MHz" },
	{ "start": "746 MHz", "end": "806 MHz" },
	{ "start": "806 MHz", "end": "890 MHz" },
	{ "start": "890 MHz", "end": "902 MHz" },
	{ "start": "902 MHz", "end": "928 MHz" },
	{ "start": "928 MHz", "end": "929 MHz" },
	{ "start": "929 MHz", "end": "932 MHz" },
	{ "start": "932 MHz", "end": "932.5 MHz" },
	{ "start": "932.5 MHz", "end": "935 MHz" },
	{ "start": "935 MHz", "end": "941 MHz" },
	{ "start": "941 MHz", "end": "941.5 MHz" },
	{ "start": "941.5 MHz", "end": "942 MHz" },
	{ "start": "942 MHz", "end": "944 MHz" },
	{ "start": "944 MHz", "end": "952 MHz" },
	{ "start": "952 MHz", "end": "956 MHz" },
	{ "start": "956 MHz", "end": "960 MHz" },
	{ "start": "960 MHz", "end": "1164 MHz" },
	{ "start": "1164 MHz", "end": "1215 MHz" },
	{ "start": "1215 MHz", "end": "1240 MHz" },
	{ "start": "1240 MHz", "end": "1300 MHz" },
	{ "start": "1300 MHz", "end": "1350 MHz" },
	{ "start": "1350 MHz", "end": "1390 MHz" },
	{ "start": "1390 MHz", "end": "1400 MHz" },
	{ "start": "1400 MHz", "end": "1427 MHz" },
	{ "start": "1427 MHz", "end": "1429 MHz" },
	{ "start": "1429 MHz", "end": "1452 MHz" },
	{ "start": "1452 MHz", "end": "1492 MHz" },
	{ "start": "1492 MHz", "end": "1518 MHz" },
	{ "start": "1518 MHz", "end": "1525 MHz" },
	{ "start": "1525 MHz", "end": "1530 MHz" },
	{ "start": "1530 MHz", "end": "1535 MHz" },
	{ "start": "1535 MHz", "end": "1559 MHz" },
	{ "start": "1559 MHz", "end": "1610 MHz" },
	{ "start": "1610 MHz", "end": "1610.6 MHz" },
	{ "start": "1610.6 MHz", "end": "1613.8 MHz" },
	{ "start": "1613.8 MHz", "end": "1626.5 MHz" },
	{ "start": "1626.5 MHz", "end": "1660 MHz" },
	{ "start": "1660 MHz", "end": "1660.5 MHz" },
	{ "start": "1660.5 MHz", "end": "1668 MHz" },
	{ "start": "1668 MHz", "end": "1668.4 MHz" },
	{ "start": "1668.4 MHz", "end": "1670 MHz" },
	{ "start": "1670 MHz", "end": "1675 MHz" },
	{ "start": "1675 MHz", "end": "1700 MHz" },
	{ "start": "1700 MHz", "end": "1710 MHz" },
	{ "start": "1710 MHz", "end": "1755 MHz" },
	{ "start": "1755 MHz", "end": "1850 MHz" },
	{ "start": "1850 MHz", "end": "2000 MHz" },
	{ "start": "2000 MHz", "end": "2020 MHz" },
	{ "start": "2020 MHz", "end": "2025 MHz" },
	{ "start": "2025 MHz", "end": "2110 MHz" },
	{ "start": "2110 MHz", "end": "2120 MHz" },
	{ "start": "2120 MHz", "end": "2180 MHz" },
	{ "start": "2180 MHz", "end": "2200 MHz" },
	{ "start": "2200 MHz", "end": "2290 MHz" },
	{ "start": "2290 MHz", "end": "2300 MHz" },
	{ "start": "2300 MHz", "end": "2450 MHz" },
	{ "start": "2450 MHz", "end": "2483.5 MHz" },
	{ "start": "2483.5 MHz", "end": "2500 MHz" },
	{ "start": "2500 MHz", "end": "2596 MHz" },
	{ "start": "2596 MHz", "end": "2655 MHz" },
	{ "start": "2655 MHz", "end": "2686 MHz" },
	{ "start": "2686 MHz", "end": "2690 MHz" },
	{ "start": "2690 MHz", "end": "2700 MHz" },
	{ "start": "2700 MHz", "end": "2900 MHz" },
	{ "start": "2900 MHz", "end": "3100 MHz" },
	{ "start": "3100 MHz", "end": "3300 MHz" },
	{ "start": "3300 MHz", "end": "3450 MHz" },
	{ "start": "3450 MHz", "end": "3500 MHz" },
	{ "start": "3500 MHz", "end": "3650 MHz" },
	{ "start": "3650 MHz", "end": "3700 MHz" },
	{ "start": "3700 MHz", "end": "4200 MHz" },
	{ "start": "4200 MHz", "end": "4400 MHz" },
	{ "start": "4400 MHz", "end": "4500 MHz" },
	{ "start": "4500 MHz", "end": "4800 MHz" },
	{ "start": "4800 MHz", "end": "4825 MHz" },
	{ "start": "4825 MHz", "end": "4835 MHz" },
	{ "start": "4835 MHz", "end": "4950 MHz" },
	{ "start": "4950 MHz", "end": "4990 MHz" },
	{ "start": "4990 MHz", "end": "5000 MHz" },
	{ "start": "5000 MHz", "end": "5010 MHz" },
	{ "start": "5010 MHz", "end": "5030 MHz" },
	{ "start": "5030 MHz", "end": "5091 MHz" },
	{ "start": "5091 MHz", "end": "5150 MHz" },
	{ "start": "5150 MHz", "end": "5250 MHz" },
	{ "start": "5250 MHz", "end": "5255 MHz" },
	{ "start": "5255 MHz", "end": "5350 MHz" },
	{ "start": "5350 MHz", "end": "5460 MHz" },
	{ "start": "5460 MHz", "end": "5470 MHz" },
	{ "start": "5470 MHz", "end": "5570 MHz" },
	{ "start": "5570 MHz", "end": "5650 MHz" },
	{ "start": "5650 MHz", "end": "5725 MHz" },
	{ "start": "5725 MHz", "end": "5850 MHz" },
	{ "start": "5850 MHz", "end": "5925 MHz" },
	{ "start": "5925 MHz", "end": "6700 MHz" },
	{ "start": "6700 MHz", "end": "7075 MHz" },
	{ "start": "7075 MHz", "end": "7145 MHz" },
	{ "start": "7145 MHz", "end": "7235 MHz" },
	{ "start": "7235 MHz", "end": "7250 MHz" },
	{ "start": "7250 MHz", "end": "7300 MHz" },
	{ "start": "7300 MHz", "end": "7450 MHz" },
	{ "start": "7450 MHz", "end": "7550 MHz" },
	{ "start": "7550 MHz", "end": "7750 MHz" },
	{ "start": "7750 MHz", "end": "7850 MHz" },
	{ "start": "7850 MHz", "end": "7900 MHz" },
	{ "start": "7900 MHz", "end": "7975 MHz" },
	{ "start": "7975 MHz", "end": "8025 MHz" },
	{ "start": "8025 MHz", "end": "8175 MHz" },
	{ "start": "8175 MHz", "end": "8215 MHz" },
	{ "start": "8215 MHz", "end": "8400 MHz" },
	{ "start": "8400 MHz", "end": "8500 MHz" },
	{ "start": "8500 MHz", "end": "8550 MHz" },
	{ "start": "8550 MHz", "end": "8650 MHz" },
	{ "start": "8650 MHz", "end": "8750 MHz" },
	{ "start": "8750 MHz", "end": "8850 MHz" },
	{ "start": "8850 MHz", "end": "9000 MHz" },
	{ "start": "9000 MHz", "end": "9200 MHz" },
	{ "start": "9200 MHz", "end": "9300 MHz" },
	{ "start": "9300 MHz", "end": "9500 MHz" },
	{ "start": "9.5 GHz", "end": "9.8 GHz" },
	{ "start": "9.8 GHz", "end": "9.9 GHz" },
	{ "start": "9.9 GHz", "end": "10 GHz" },
	{ "start": "10 GHz", "end": "10.45 GHz" },
	{ "start": "10.45 GHz", "end": "10.5 GHz" },
	{ "start": "10.5 GHz", "end": "10.55 GHz" },
	{ "start": "10.55 GHz", "end": "10.6 GHz" },
	{ "start": "10.6 GHz", "end": "10.68 GHz" },
	{ "start": "10.68 GHz", "end": "10.7 GHz" },
	{ "start": "10.7 GHz", "end": "11.7 GHz" },
	{ "start": "11.7 GHz", "end": "12.2 GHz" },
	{ "start": "12.2 GHz", "end": "12.7 GHz" },
	{ "start": "12.7 GHz", "end": "12.75 GHz" },
	{ "start": "12.75 GHz", "end": "13.25 GHz" },
	{ "start": "13.25 GHz", "end": "13.4 GHz" },
	{ "start": "13.4 GHz", "end": "13.75 GHz" },
	{ "start": "13.75 GHz", "end": "14 GHz" },
	{ "start": "14 GHz", "end": "14.47 GHz" },
	{ "start": "14.47 GHz", "end": "14.5 GHz" },
	{ "start": "14.5 GHz", "end": "14.66 GHz" },
	{ "start": "14.66 GHz", "end": "14.82 GHz" },
	{ "start": "14.82 GHz", "end": "15.135 GHz" },
	{ "start": "15.135 GHz", "end": "15.295 GHz" },
	{ "start": "15.295 GHz", "end": "15.35 GHz" },
	{ "start": "15.35 GHz", "end": "15.4 GHz" },
	{ "start": "15.4 GHz", "end": "15.43 GHz" },
	{ "start": "15.43 GHz", "end": "15.63 GHz" },
	{ "start": "15.63 GHz", "end": "15.7 GHz" },
	{ "start": "15.7 GHz", "end": "16.6 GHz" },
	{ "start": "16.6 GHz", "end": "17.1 GHz" },
	{ "start": "17.1 GHz", "end": "17.2 GHz" },
	{ "start": "17.2 GHz", "end": "17.3 GHz" },
	{ "start": "17.3 GHz", "end": "17.7 GHz" },
	{ "start": "17.7 GHz", "end": "17.8 GHz" },
	{ "start": "17.8 GHz", "end": "18.1 GHz" },
	{ "start": "18.1 GHz", "end": "18.4 GHz" },
	{ "start": "18.4 GHz", "end": "18.6 GHz" },
	{ "start": "18.6 GHz", "end": "18.8 GHz" },
	{ "start": "18.8 GHz", "end": "19.3 GHz" },
	{ "start": "19.3 GHz", "end": "19.7 GHz" },
	{ "start": "19.7 GHz", "end": "20.2 GHz" },
	{ "start": "20.2 GHz", "end": "21.2 GHz" },
	{ "start": "21.2 GHz", "end": "21.4 GHz" },
	{ "start": "21.4 GHz", "end": "22 GHz" },
	{ "start": "22 GHz", "end": "22.21 GHz" },
	{ "start": "22.21 GHz", "end": "22.5 GHz" },
	{ "start": "22.5 GHz", "end": "22.55 GHz" },
	{ "start": "22.55 GHz", "end": "23.55 GHz" },
	{ "start": "23.55 GHz", "end": "23.6 GHz" },
	{ "start": "23.6 GHz", "end": "24 GHz" },
	{ "start": "24 GHz", "end": "24.05 GHz" },
	{ "start": "24.05 GHz", "end": "24.25 GHz" },
	{ "start": "24.25 GHz", "end": "24.45 GHz" },
	{ "start": "24.45 GHz", "end": "24.65 GHz" },
	{ "start": "24.65 GHz", "end": "24.75 GHz" },
	{ "start": "24.75 GHz", "end": "25.05 GHz" },
	{ "start": "25.05 GHz", "end": "25.25 GHz" },
	{ "start": "25.25 GHz", "end": "25.5 GHz" },
	{ "start": "25.5 GHz", "end": "27 GHz" },
	{ "start": "27 GHz", "end": "27.5 GHz" },
	{ "start": "27.5 GHz", "end": "28.5 GHz" },
	{ "start": "28.5 GHz", "end": "29.1 GHz" },
	{ "start": "29.1 GHz", "end": "29.5 GHz" },
	{ "start": "29.5 GHz", "end": "29.9 GHz" },
	{ "start": "29.9 GHz", "end": "30 GHz" },
	{ "start": "30 GHz", "end": "31 GHz" },
	{ "start": "31 GHz", "end": "31.3 GHz" },
	{ "start": "31.3 GHz", "end": "31.8 GHz" },
	{ "start": "31.8 GHz", "end": "32 GHz" },
	{ "start": "32 GHz", "end": "32.3 GHz" },
	{ "start": "32.3 GHz", "end": "33 GHz" },
	{ "start": "33 GHz", "end": "33.4 GHz" },
	{ "start": "33.4 GHz", "end": "34.2 GHz" },
	{ "start": "34.2 GHz", "end": "34.7 GHz" },
	{ "start": "34.7 GHz", "end": "35.2 GHz" },
	{ "start": "35.2 GHz", "end": "35.5 GHz" },
	{ "start": "35.5 GHz", "end": "36 GHz" },
	{ "start": "36 GHz", "end": "37 GHz" },
	{ "start": "37 GHz", "end": "37.5 GHz" },
	{ "start": "37.5 GHz", "end": "38 GHz" },
	{ "start": "38 GHz", "end": "39.5 GHz" },
	{ "start": "39.5 GHz", "end": "40 GHz" },
	{ "start": "40 GHz", "end": "40.5 GHz" },
	{ "start": "40.5 GHz", "end": "41 GHz" },
	{ "start": "41 GHz", "end": "42.5 GHz" },
	{ "start": "42.5 GHz", "end": "43.5 GHz" },
	{ "start": "43.5 GHz", "end": "47 GHz" },
	{ "start": "47 GHz", "end": "47.2 GHz" },
	{ "start": "47.2 GHz", "end": "47.5 GHz" },
	{ "start": "47.5 GHz", "end": "47.9 GHz" },
	{ "start": "47.9 GHz", "end": "48.2 GHz" },
	{ "start": "48.2 GHz", "end": "50.2 GHz" },
	{ "start": "50.2 GHz", "end": "50.4 GHz" },
	{ "start": "50.4 GHz", "end": "51.4 GHz" },
	{ "start": "51.4 GHz", "end": "52.6 GHz" },
	{ "start": "52.6 GHz", "end": "54.25 GHz" },
	{ "start": "54.25 GHz", "end": "55.78 GHz" },
	{ "start": "55.78 GHz", "end": "56.9 GHz" },
	{ "start": "56.9 GHz", "end": "57 GHz" },
	{ "start": "57 GHz", "end": "58.2 GHz" },
	{ "start": "58.2 GHz", "end": "59 GHz" },
	{ "start": "59 GHz", "end": "59.3 GHz" },
	{ "start": "59.3 GHz", "end": "64 GHz" },
	{ "start": "64 GHz", "end": "65 GHz" },
	{ "start": "65 GHz", "end": "66 GHz" },
	{ "start": "66 GHz", "end": "71 GHz" },
	{ "start": "71 GHz", "end": "74 GHz" },
	{ "start": "74 GHz", "end": "76 GHz" },
	{ "start": "76 GHz", "end": "77.5 GHz" },
	{ "start": "77.5 GHz", "end": "78 GHz" },
	{ "start": "78 GHz", "end": "79 GHz" },
	{ "start": "79 GHz", "end": "81 GHz" },
	{ "start": "81 GHz", "end": "84 GHz" },
	{ "start": "84 GHz", "end": "86 GHz" },
	{ "start": "86 GHz", "end": "92 GHz" },
	{ "start": "92 GHz", "end": "94 GHz" },
	{ "start": "94 GHz", "end": "94.1 GHz" },
	{ "start": "94.1 GHz", "end": "95 GHz" },
	{ "start": "95 GHz", "end": "100 GHz" },
	{ "start": "100 GHz", "end": "102 GHz" },
	{ "start": "102 GHz", "end": "105 GHz" },
	{ "start": "105 GHz", "end": "109.5 GHz" },
	{ "start": "109.5 GHz", "end": "111.8 GHz" },
	{ "start": "111.8 GHz", "end": "114.25 GHz" },
	{ "start": "114.25 GHz", "end": "116 GHz" },
	{ "start": "116 GHz", "end": "122.25 GHz" },
	{ "start": "122.25 GHz", "end": "123 GHz" },
	{ "start": "123 GHz", "end": "130 GHz" },
	{ "start": "130 GHz", "end": "134 GHz" },
	{ "start": "134 GHz", "end": "136 GHz" },
	{ "start": "136 GHz", "end": "141 GHz" },
	{ "start": "141 GHz", "end": "148.5 GHz" },
	{ "start": "148.5 GHz", "end": "151.5 GHz" },
	{ "start": "151.5 GHz", "end": "155.5 GHz" },
	{ "start": "155.5 GHz", "end": "158.5 GHz" },
	{ "start": "158.5 GHz", "end": "164 GHz" },
	{ "start": "164 GHz", "end": "167 GHz" },
	{ "start": "167 GHz", "end": "174.5 GHz" },
	{ "start": "174.5 GHz", "end": "174.8 GHz" },
	{ "start": "174.8 GHz", "end": "182 GHz" },
	{ "start": "182 GHz", "end": "185 GHz" },
	{ "start": "185 GHz", "end": "190 GHz" },
	{ "start": "190 GHz", "end": "191.8 GHz" },
	{ "start": "191.8 GHz", "end": "200 GHz" },
	{ "start": "200 GHz", "end": "202 GHz" },
	{ "start": "202 GHz", "end": "209 GHz" },
	{ "start": "209 GHz", "end": "217 GHz" },
	{ "start": "217 GHz", "end": "226 GHz" },
	{ "start": "226 GHz", "end": "231.5 GHz" },
	{ "start": "231.5 GHz", "end": "232 GHz" },
	{ "start": "232 GHz", "end": "235 GHz" },
	{ "start": "235 GHz", "end": "238 GHz" },
	{ "start": "238 GHz", "end": "240 GHz" },
	{ "start": "240 GHz", "end": "241 GHz" },
	{ "start": "241 GHz", "end": "248 GHz" },
	{ "start": "248 GHz", "end": "250 GHz" },
	{ "start": "250 GHz", "end": "252 GHz" },
	{ "start": "252 GHz", "end": "265 GHz" },
	{ "start": "265 GHz", "end": "275 GHz" },
	]
}